{
    "Navigation": {
      "App" : [
        {
          "Id": 0,
          "Name": "Estimating",
          "Description": "Estimating description",
          "icon": "icon-estimating.png",

          "MenuItem": [
            {
              "Text": "Estimating",
              "Claim": "http://rootssoftware.com/module/estimating",
              "icon": "fa-calculator",
              "MenuItem": [
                {
                  "Text": "Users",
                  "Url": "/users",
                  "Claim": "Nav_Users"
                },
                {
                  "Text": "Budgets",
                  "Url": "/budgets",
                  "Claim": "Nav_Budget"
                },
                {
                  "Text": "Estimates",
                  "Url": "/estimates",
                  "Claim": "Nav_Estimates"
                },
                {
                  "Text": "Change Orders",
                  "Url": "/cors",
                  "Claim": "Nav_CORS"
                },
                {
                  "Text": "Files",
                  "Url": "/files",
                  "Claim": "Nav_Files"
                },
                {
                  "Text": "Codes",
                  "Url": "/codes",
                  "Claim": "Nav_Codes"
                },
                {
                  "Text": "Tree",
                  "Url": "/tree",
                  "Claim": "Nav_Tree"
                }
              ]
            },
            {
              "Text": "Heroes",
              "Claim": "http://rootssoftware.com/module/projectmanagement",
              "icon": "fa-mask",
              "MenuItem": [
                {
                  "Text": "Heroes",
                  "Url": "/superheroes/heroes",
                  "Claim": "Nav_Heroes"
                },
                {
                  "Text": "Teams",
                  "Url": "/superheroes/teams",
                  "Claim": "Nav_Teams"
                }


              ]
            },
            {
              "Text": "Accounting",
              "Claim": "http://rootssoftware.com/module/accounting",
              "icon": "fa-dollar-sign",
              "MenuItem": [
                {
                  "Text": "Accounts Payable",
                  "Url": "/leads/calendar",
                  "Claim": "Nav_Tags"
                },
                {
                  "Text": "Accounts Receivable",
                  "Url": "/leads",
                  "Claim": "Nav_Tags"
                }
              ]
            },
            {
              "Text": "Charts",
              "Claim": "http://rootssoftware.com/module/charts",
              "icon": "fa-chart-bar",
              "MenuItem": [
                {
                  "Text": "Line",
                  "Url": "/line-chart",
                  "Claim": "Nav_Line-Chart"
                },
                {
                  "Text": "Bar",
                  "Url": "/bar-chart",
                  "Claim": "Nav_Bar-Chart"
                },
                {
                  "Text": "Pie",
                  "Url": "/pie-chart",
                  "Claim": "Nav_Bar-Chart"
                }
              ]
            },
            {
              "Text": "Sandbox",
              "Claim": "http://rootssoftware/development/sandbox",
              "icon": "fa-cat",
              "MenuItem": [
                {
                  "Text": "Answers",
                  "Url": "/answers",
                  "Claim": "Nav_Answers"
                },
                {
                  "Text": "Movies",
                  "Url": "/movies",
                  "Claim": "Nav_Movies"
                },
                {
                  "Text": "Alerts",
                  "Url": "/about",
                  "Claim": "Nav_About"
                },
                {
                  "Text": "List",
                  "Url": "/list",
                  "Claim": "Nav_List"
                },
                {
                  "Text": "Infinite Scroll",
                  "Url": "/infinite-scroll",
                  "Claim": "Nav_List"
                }
              ]
            },
            {
              "Text": "Settings",
              "Claim": "http://rootssoftware/development/sandbox",
              "icon": "fa-cog",
              "MenuItem": [
                {
                  "Text": "App",
                  "Url": "/app",
                  "Claim": "Nav_App"
                }
              ]
            }

          ]
        },

        {
          "Id": 1,
          "Name": "Construct",
          "Description": "Construct description",
          "icon": "icon-construct.png",

          "MenuItem": [
            {
              "Text": "RFI",
              "Claim": "http://rootssoftware.com/module/estimating",
              "icon": "fa-book",
              "MenuItem": [
                {
                  "Text": "Calendar",
                  "Url": "/calendar",
                  "Claim": "Nav_Calendar"
                },
                {
                  "Text": "Tables",
                  "Url": "/tables",
                  "Claim": "Nav_Tables"
                },
                {
                  "Text": "Estimates",
                  "Url": "/estimates",
                  "Claim": "Nav_Estimates"
                },

                {
                  "Text": "Flex",
                  "Url": "/flex1",
                  "Claim": "Nav_Flex"
                },
                {
                  "Text": "Picker",
                  "Url": "picker",
                  "Claim": "Picker"
                },

                {
                  "Text": "Markups",
                  "Url": "/leads/markups",
                  "Claim": "Nav_Tags"
                },
                {
                  "Text": "Estimate Summary",
                  "Url": "/leads/estimatesummary",
                  "Claim": "Nav_Tags"
                },
                {
                  "Text": "Project Documents",
                  "Url": "/leads/estimatedocuments",
                  "Claim": "Nav_Tags"
                }
              ]
            },
            {
              "Text": "RFI Tasks",
              "Claim": "http://rootssoftware.com/module/projectmanagement",
              "icon": "fa-book-open",
              "MenuItem": [
                {
                  "Text": "Team",
                  "Url": "/team",
                  "Claim": "Nav_Teams"
                },
                {
                  "Text": "RFI",
                  "Url": "/rfi",
                  "Claim": "Nav_Rfi"
                },
                {
                  "Text": "Submittals",
                  "Url": "/leads/estimates",
                  "Claim": "Nav_Tags"
                },
                {
                  "Text": "Issues",
                  "Url": "/leads/scope",
                  "Claim": "Nav_Tags"
                },
                {
                  "Text": "Change Orders",
                  "Url": "/cors",
                  "Claim": "Nav_CORS"
                },
                {
                  "Text": "Cost Control",
                  "Url": "/leads/bidtabs",
                  "Claim": "Nav_Tags"
                },
                {
                  "Text": "Labor Reporting",
                  "Url": "/leads/general",
                  "Claim": "Nav_Tags"
                },
                {
                  "Text": "Schedule of Values",
                  "Url": "/leads/markups",
                  "Claim": "Nav_Tags"
                }
              ]
            },
            {
              "Text": "Observations",
              "Claim": "http://rootssoftware.com/module/accounting",
              "icon": "fa-bullseye",
              "MenuItem": [
                {
                  "Text": "Accounts Payable",
                  "Url": "/leads/calendar",
                  "Claim": "Nav_Tags"
                },
                {
                  "Text": "Accounts Receivable",
                  "Url": "/leads",
                  "Claim": "Nav_Tags"
                }
              ]
            },
            {
              "Text": "Inspections",
              "Claim": "http://rootssoftware.com/module/contacts",
              "icon": "fa-calendar-check",
              "MenuItem": [
                {
                  "Text": "Companies",
                  "Url": "/leads/calendar",
                  "Claim": "Nav_Tags"
                },
                {
                  "Text": "Contacts",
                  "Url": "/leads",
                  "Claim": "Nav_Tags"
                }
              ]
            },
            {
              "Text": "Submittals",
              "Claim": "http://rootssoftware/development/sandbox",
              "icon": "fa-archive",
              "MenuItem": [
                {
                  "Text": "Answers",
                  "Url": "/answers",
                  "Claim": "Nav_Answers"
                },
                {
                  "Text": "Movies",
                  "Url": "/movies",
                  "Claim": "Nav_Movies"
                }
              ]
            },
            {
              "Text": "Safety",
              "Claim": "http://rootssoftware/development/sandbox",
              "icon": "fa-band-aid",
              "MenuItem": [
                {
                  "Text": "Company",
                  "Url": "/company",
                  "Claim": "Nav_Company"
                }

              ]
            },
            {
              "Text": "Photos",
              "Claim": "http://rootssoftware/development/sandbox",
              "icon": "fa-camera",
              "MenuItem": [
                {
                  "Text": "Company",
                  "Url": "/company",
                  "Claim": "Nav_Company"
                }

              ]
            }

          ]
        },

        {
          "Id": 2,
          "Name": "Design",
          "Description": "Design description",
          "icon": "icon-design.png",

          "MenuItem": [
            {
              "Text": "Design One",
              "Claim": "http://rootssoftware.com/module/estimating",
              "icon": "fa-drafting-compass",
              "MenuItem": [
                {
                  "Text": "Design",
                  "Url": "/calendar",
                  "Claim": "Nav_Calendar"
                }
              ]
            }
          ]
        },

        {
          "Id": 3,
          "Name": "Insight",
          "Description": "Insight description",
          "icon": "icon-insight.png",

          "MenuItem": [
            {
              "Text": "Insight One",
              "Claim": "http://rootssoftware.com/module/estimating",
              "icon": "fa-couch",
              "MenuItem": [
                {
                  "Text": "Insight",
                  "Url": "/calendar",
                  "Claim": "Nav_Calendar"
                }
              ]
            }
          ]
        },

        {
          "Id": 4,
          "Name": "Connect",
          "Description": "Connect description",
          "icon": "icon-connect.png",

          "MenuItem": [
            {
              "Text": "Connect One",
              "Claim": "http://rootssoftware.com/module/estimating",
              "icon": "fa-cubes",
              "MenuItem": [
                {
                  "Text": "Insight",
                  "Url": "/calendar",
                  "Claim": "Nav_Calendar"
                },
                {
                  "Text": "Dain",
                  "Url": "/dain",
                  "Claim": "Nav_Dain"
                }
              ]
            }
          ]
        }



      ]
    }
  }
